annotatedyaml/__init__.py
annotatedyaml/const.py
annotatedyaml/constructors.cpython-313-aarch64-linux-musl.so
annotatedyaml/constructors.pxd
annotatedyaml/constructors.py
annotatedyaml/dumper.py
annotatedyaml/exceptions.py
annotatedyaml/input.py
annotatedyaml/loader.py
annotatedyaml/objects.py
annotatedyaml/py.typed
annotatedyaml/reference.cpython-313-aarch64-linux-musl.so
annotatedyaml/reference.pxd
annotatedyaml/reference.py
annotatedyaml/reference_object.py
annotatedyaml-1.0.0.dist-info/LICENSE
annotatedyaml-1.0.0.dist-info/METADATA
annotatedyaml-1.0.0.dist-info/WHEEL
annotatedyaml-1.0.0.dist-info/RECORD
