Metadata-Version: 2.3
Name: annotatedyaml
Version: 1.0.0
Summary: Annotated YAML that supports secrets for Python
License: Apache-2.0
Author: Home Assistant Devs
Author-email: hello@home-assistant.io
Requires-Python: >=3.13
Classifier: Development Status :: 2 - Pre-Alpha
Classifier: Intended Audience :: Developers
Classifier: Natural Language :: English
Classifier: Operating System :: OS Independent
Classifier: Programming Language :: Python :: 3.13
Classifier: Topic :: Software Development :: Libraries
Requires-Dist: propcache (>0.1)
Requires-Dist: pyyaml (>=6.0.1)
Requires-Dist: voluptuous (>0.15)
Project-URL: Bug Tracker, https://github.com/home-assistant-libs/annotatedyaml/issues
Project-URL: Changelog, https://github.com/home-assistant-libs/annotatedyaml/blob/main/CHANGELOG.md
Project-URL: Documentation, https://annotatedyaml.readthedocs.io
Project-URL: Repository, https://github.com/home-assistant-libs/annotatedyaml
